README
setup.py
lmtoolkit/__init__.py
lmtoolkit/df.py
lmtoolkit/feature.py
lmtoolkit/importances.py
lmtoolkit/model.py
lmtoolkit/pipeline.py
lmtoolkit/scorer.py
lmtoolkit/tuner.py
lmtoolkit/utils.py
lmtoolkit/xl.py
lmtoolkit.egg-info/PKG-INFO
lmtoolkit.egg-info/SOURCES.txt
lmtoolkit.egg-info/dependency_links.txt
lmtoolkit.egg-info/not-zip-safe
lmtoolkit.egg-info/top_level.txt