Metadata-Version: 1.0
Name: lmtoolkit
Version: 0.1.19
Summary: Macro scripts for kaggle competitions
Home-page: https://github.com/luthfim/lmtoolkit
Author: Luthfi Mahendra
Author-email: luthfimaa@gmail.com
License: MIT
Platform: UNKNOWN
